[{"type":"function","name":"quoteExactInputSingle","constant":false,"payable":false,"inputs":[{"type":"tuple","name":"params","components":[{"type":"address","name":"tokenIn"},{"type":"address","name":"tokenOut"},{"type":"uint256","name":"amountIn"},{"type":"uint24","name":"fee"},{"type":"uint160","name":"sqrtPriceLimitX96"}]}],"outputs":[{"type":"uint256","name":"amountOut"},{"type":"uint160","name":"sqrtPriceX96After"},{"type":"uint32","name":"initializedTicksCrossed"},{"type":"uint256","name":"gasEstimate"}]}]